latss/__init__.py
latss/latss.py
latss/data/__init__.py
latss/data/load_data.py
latss/label_alignment/__init__.py
latss/label_alignment/la.py
latss/preprocessing/__init__.py
latss/preprocessing/epochs_preprocessing.py
latss/preprocessing/raw_preprocessing.py
latss/tsmapping/__init__.py
latss/tsmapping/tsm.py
latss/utils/__init__.py
latss/utils/utils.py
latss-0.1.5.dist-info/LICENSE
latss-0.1.5.dist-info/METADATA
latss-0.1.5.dist-info/WHEEL
latss-0.1.5.dist-info/top_level.txt
latss-0.1.5.dist-info/RECORD
