Metadata-Version: 2.1
Name: latss
Version: 0.1.5
Summary: Unlocking subject-independent motor imagery decoding with label alignment.
Author-email: Zeyad Ahmed <zeyadmansour2@gmail.com>
License: MIT License
Project-URL: Homepage, https://pypi.org/project/latss/
Project-URL: Repository, https://github.com/zeyadmohaymen/latss.git
Keywords: motor imagery,EEG,label alignment
Classifier: Development Status :: 3 - Alpha
Classifier: License :: OSI Approved :: MIT License
Classifier: Programming Language :: Python
Requires-Python: >=3.8
License-File: LICENSE
Requires-Dist: pyriemann
Requires-Dist: scipy >=1.10.1
Requires-Dist: mne
Requires-Dist: mne-icalabel
Requires-Dist: onnxruntime
